Workbook

Sheet Summary
A1: Operation Blue Tiger: Milestone 1
A3: Mod | B3: Millennium Dawn: Developer Version
A4: Descriptor version | B4: 2.0.0 (changelog in progress: v2.0.1)
A5: HOI4 supported | B5: 1.19.*
A6: Repository | B6: D:\Projects\Millennium-Dawn
A7: Branch | B7: obt-taiwan-overhaul
A8: Base commit | B8: f198c6c8db (upstream main, 2 Oct 2026)
A11: Branch | B11: Focuses | C11: Total days | D11: In-game tested
A12: The 2000 Succession | B12: =COUNTIF(Focuses!$C$2:$C$248,A12) -> 41 | C12: =SUMIF(Focuses!$C$2:$C$248,A12,Focuses!$E$2:$E$248) -> 2485 | D12: =COUNTIFS(Focuses!$C$2:$C$248,A12,Focuses!$L$2:$L$248,"In-game tested") -> 0
A13: Democratic Fortress | B13: =COUNTIF(Focuses!$C$2:$C$248,A13) -> 30 | C13: =SUMIF(Focuses!$C$2:$C$248,A13,Focuses!$E$2:$E$248) -> 2030 | D13: =COUNTIFS(Focuses!$C$2:$C$248,A13,Focuses!$L$2:$L$248,"In-game tested") -> 0
A14: The National Army | B14: =COUNTIF(Focuses!$C$2:$C$248,A14) -> 50 | C14: =SUMIF(Focuses!$C$2:$C$248,A14,Focuses!$E$2:$E$248) -> 4095 | D14: =COUNTIFS(Focuses!$C$2:$C$248,A14,Focuses!$L$2:$L$248,"In-game tested") -> 0
A15: The Silicon Island | B15: =COUNTIF(Focuses!$C$2:$C$248,A15) -> 37 | C15: =SUMIF(Focuses!$C$2:$C$248,A15,Focuses!$E$2:$E$248) -> 2975 | D15: =COUNTIFS(Focuses!$C$2:$C$248,A15,Focuses!$L$2:$L$248,"In-game tested") -> 0
A16: Across the Strait | B16: =COUNTIF(Focuses!$C$2:$C$248,A16) -> 29 | C16: =SUMIF(Focuses!$C$2:$C$248,A16,Focuses!$E$2:$E$248) -> 2065 | D16: =COUNTIFS(Focuses!$C$2:$C$248,A16,Focuses!$L$2:$L$248,"In-game tested") -> 0
A17: The Pacific Lifeline | B17: =COUNTIF(Focuses!$C$2:$C$248,A17) -> 33 | C17: =SUMIF(Focuses!$C$2:$C$248,A17,Focuses!$E$2:$E$248) -> 2205 | D17: =COUNTIFS(Focuses!$C$2:$C$248,A17,Focuses!$L$2:$L$248,"In-game tested") -> 0
A18: Operation Blue Tiger | B18: =COUNTIF(Focuses!$C$2:$C$248,A18) -> 27 | C18: =SUMIF(Focuses!$C$2:$C$248,A18,Focuses!$E$2:$E$248) -> 1750 | D18: =COUNTIFS(Focuses!$C$2:$C$248,A18,Focuses!$L$2:$L$248,"In-game tested") -> 0
A19: Total | B19: =SUM(B12:B18) -> 247 | C19: =SUM(C12:C18) -> 17605 | D19: =SUM(D12:D18) -> 0
A21: National spirits | B21: =COUNTA(Spirits!A2:A49) -> 48
A22: Starting spirits | B22: =COUNTIF(Spirits!C2:C49,"Yes") -> 5
A24: How to use
A25: On the Focuses sheet, the yellow Status and Notes columns are yours to edit. Set Status from the dropdown (for example "In-game tested") and the In-game tested column above updates.
A26: Focus days are game days; HOI4 focus cost = days / 7.

Sheet Focuses
A1: Focus ID | B1: Name | C1: Branch | D1: Track | E1: Days | F1: Prerequisites | G1: Mutually exclusive | H1: Requirements | I1: Effects | J1: Content type | K1: AI weight | L1: Status | M1: Notes
A2: TAI_su_millennium_election | B2: The Millennium Election | C2: The 2000 Succession | D2: Shared trunk | E2: 35 | I2: +50 Political Power | J2: Historical / abstraction | K2: 10 | L2: Written
A3: TAI_su_heal_kmt_split | B3: Heal the KMT Split | C3: The 2000 Succession | D3: Shared trunk | E3: 35 | F3: The Millennium Election | G3: Let the Voters Decide | H3: Before 2000.3.18 | I3: Party 1 popularity +4%; Party 14 popularity -4%; -2% Stability | J3: Historical / abstraction | K3: 1 | L3: Written
A4: TAI_su_voters_decide | B4: Let the Voters Decide | C4: The 2000 Succession | D4: Shared trunk | E4: 35 | F4: The Millennium Election | G4: Heal the KMT Split | I4: +3% Stability; +25 Political Power | J4: Historical / abstraction | K4: 3 | L4: Written
A5: TAI_su_lee_legacy | B5: Lee Teng-hui's Legacy | C5: The 2000 Succession | D5: Shared trunk | E5: 35 | F5: The Millennium Election | I5: Taiwan-Centered Identity +5; Strait Tension (CHI) +3; +25 Political Power | J5: Historical / abstraction | K5: 1 | L5: Written
A6: TAI_su_peaceful_transfer | B6: The Peaceful Transfer of Power | C6: The 2000 Succession | D6: Shared trunk | E6: 70 | F6: Heal the KMT Split or Let the Voters Decide | H6: After the 2000 election | I6: +5% Stability; Military Confidence -5; +50 Political Power | J6: Historical / abstraction | K6: 5 | L6: Written
A7: TAI_su_form_cabinet | B7: Form the Cabinet | C7: The 2000 Succession | D7: Shared trunk | E7: 35 | F7: The Peaceful Transfer of Power | I7: Military Confidence +5; +25 Political Power | J7: Historical / abstraction | K7: 5 | L7: Written
A8: TAI_su_minority_government | B8: A Government Without a Majority | C8: The 2000 Succession | D8: Shared trunk | E8: 35 | F8: Form the Cabinet | G8: A Unified Government | H8: No LY majority | I8: Add spirit TAI_divided_government; +50 Political Power | J8: Historical / abstraction | K8: 5 | L8: Written
A9: TAI_su_unified_government | B9: A Unified Government | C9: The 2000 Succession | D9: Shared trunk | E9: 35 | F9: Form the Cabinet | G9: A Government Without a Majority | H9: LY majority | I9: +75 Political Power; -2% Stability | J9: Historical / abstraction | K9: 5 | L9: Written
A10: TAI_su_fourth_nuclear | B10: The Fourth Nuclear Plant Question | C10: The 2000 Succession | D10: Shared trunk | E10: 70 | F10: A Government Without a Majority or A Unified Government | I10: Research bonus nuclear_reactors; -2% Stability | J10: Historical / abstraction | K10: 1 | L10: Written
A11: TAI_su_2001_recession | B11: Weather the 2001 Recession | C11: The 2000 Succession | D11: Shared trunk | E11: 70 | F11: The Peaceful Transfer of Power | H11: After 2001.1.1 | I11: -3bn Treasury; +4% Stability; Timed spirit TAI_recession_relief (365 days) | J11: Historical / abstraction | K11: 3 | L11: Written
A12: TAI_su_ly_2001 | B12: The 2001 Legislative Election | C12: The 2000 Succession | D12: Shared trunk | E12: 35 | F12: A Government Without a Majority or A Unified Government | H12: After 2001.6.1 | I12: Ruling camp popularity +2%; +25 Political Power | J12: Historical / abstraction | K12: 1 | L12: Written
A13: TAI_su_second_mandate | B13: Seek a Second Mandate | C13: The 2000 Succession | D13: Shared trunk | E13: 70 | F13: The 2001 Legislative Election | H13: After 2003.6.1 | I13: Ruling camp popularity +2%; +2% Stability | J13: Historical / abstraction | K13: 1 | L13: Written
A14: TAI_su_heal_divided_island | B14: Healing a Divided Island | C14: The 2000 Succession | D14: Shared trunk | E14: 70 | F14: Seek a Second Mandate | H14: After 2004.3.21 | I14: +5% Stability; Pressure to Negotiate -3 | J14: Historical / abstraction | K14: 1 | L14: Written
A15: TAI_su_second_test | B15: Democracy's Second Test | C15: The 2000 Succession | D15: Shared trunk | E15: 70 | F15: Healing a Divided Island | H15: After 2007.6.1 | I15: +4% Stability; +50 Political Power | J15: Historical / abstraction | K15: 1 | L15: Written
A16: TAI_su_dpp_four_noes | B16: Four Noes and One Without | C16: The 2000 Succession | D16: DPP path | E16: 35 | F16: Form the Cabinet | H16: Pan-Green governing | I16: Strait Tension (CHI) -8; U.S. Confidence in Taipei +10; Cross-Strait Trust (CHI) +5 | J16: Historical / abstraction | K16: 5 | L16: Written
A17: TAI_su_dpp_cautious_revolutionary | B17: The Cautious Revolutionary | C17: The 2000 Succession | D17: DPP path | E17: 70 | F17: Four Noes and One Without | H17: Pan-Green governing | I17: +3% Stability; Military Confidence +5; +50 Political Power | J17: Historical / abstraction | K17: 3 | L17: Written
A18: TAI_su_dpp_taiwan_centered | B18: A Taiwan-Centered State | C18: The 2000 Succession | D18: DPP path | E18: 70 | F18: The Cautious Revolutionary | H18: Pan-Green governing | I18: Taiwan-Centered Identity +8; Strait Tension (CHI) +4; Cross-Strait Trust (CHI) -4 | J18: Historical / abstraction | K18: 1 | L18: Written
A19: TAI_su_dpp_referendum_act | B19: The Referendum Act | C19: The 2000 Succession | D19: DPP path | E19: 70 | F19: A Taiwan-Centered State | H19: Pan-Green governing; Can pass legislation (LY); After 2003.1.1 | I19: Taiwan-Centered Identity +3; U.S. Confidence in Taipei -5; +2% Stability | J19: Historical / abstraction | K19: 1 | L19: Written
A20: TAI_su_dpp_status_quo | B20: Reaffirm the Status Quo | C20: The 2000 Succession | D20: DPP path | E20: 70 | F20: The Referendum Act | G20: Name Rectification | H20: Pan-Green governing | I20: U.S. Confidence in Taipei +10; Strait Tension (CHI) -5; -3% Stability | J20: Historical / abstraction | K20: 3 | L20: Written
A21: TAI_su_dpp_name_rectification | B21: Name Rectification | C21: The 2000 Succession | D21: DPP path | E21: 70 | F21: The Referendum Act | G21: Reaffirm the Status Quo | H21: Pan-Green governing | I21: Taiwan-Centered Identity +10; Strait Tension (CHI) +10; U.S. Confidence in Taipei -10 | J21: Historical / abstraction | K21: 1 | L21: Written
A22: TAI_su_dpp_council_ceases | B22: The Council Ceases to Function | C22: The 2000 Succession | D22: DPP path | E22: 70 | F22: Name Rectification | H22: Pan-Green governing; Strait Tension above 49 | I22: Taiwan-Centered Identity +5; Strait Tension (CHI) +12; U.S. Confidence in Taipei -10 | J22: Historical / abstraction | K22: 1 | L22: Written
A23: TAI_su_dpp_un_bid | B23: Join the UN as Taiwan | C23: The 2000 Succession | D23: DPP path | E23: 70 | F23: The Council Ceases to Function | H23: Pan-Green governing; After 2007.1.1 | I23: Taiwan-Centered Identity +10; U.S. Confidence in Taipei -15; Strait Tension (CHI) +10 | J23: Historical / abstraction | K23: 0 | L23: Written
A24: TAI_su_dpp_clean_party | B24: A Clean Green Party | C24: The 2000 Succession | D24: DPP path | E24: 70 | F24: The Cautious Revolutionary | H24: Pan-Green governing | I24: Corruption -1 level; +2% Stability | J24: Historical / abstraction | K24: 3 | L24: Written
A25: TAI_su_kmt_rebuild | B25: Rebuild the Kuomintang | C25: The 2000 Succession | D25: KMT path | E25: 70 | F25: Form the Cabinet | H25: KMT governing | I25: +3% Stability; +50 Political Power | J25: Historical / abstraction | K25: 5 | L25: Written
A26: TAI_su_kmt_party_assets | B26: Settle the Party Assets | C26: The 2000 Succession | D26: KMT path | E26: 70 | F26: Rebuild the Kuomintang | H26: KMT governing | I26: Corruption -1 level; +3% Stability | J26: Historical / abstraction | K26: 1 | L26: Written
A27: TAI_su_kmt_technocrats | B27: A Government of Technocrats | C27: The 2000 Succession | D27: KMT path | E27: 70 | F27: Rebuild the Kuomintang | H27: KMT governing | I27: Reform Capacity +10; Timed spirit TAI_technocratic_cabinet (730 days) | J27: Historical / abstraction | K27: 3 | L27: Written
A28: TAI_su_kmt_pan_blue | B28: The Pan-Blue Coalition | C28: The 2000 Succession | D28: KMT path | E28: 35 | F28: Rebuild the Kuomintang | H28: KMT governing | I28: Party 1 popularity +2%; Party 14 popularity +1%; +25 Political Power | J28: Historical / abstraction | K28: 3 | L28: Written
A29: TAI_su_kmt_new_taiwanese | B29: We Are All New Taiwanese | C29: The 2000 Succession | D29: KMT path | E29: 70 | F29: The Pan-Blue Coalition | H29: KMT governing | I29: Taiwan-Centered Identity +4; +3% Stability | J29: Historical / abstraction | K29: 1 | L29: Written
A30: TAI_su_kmt_roc_framework | B30: Preserve the ROC Framework | C30: The 2000 Succession | D30: KMT path | E30: 70 | F30: We Are All New Taiwanese | H30: KMT governing | I30: Strait Tension (CHI) -5; Cross-Strait Trust (CHI) +5 | J30: Historical / abstraction | K30: 1 | L30: Written
A31: TAI_su_kmt_peace_framework | B31: Toward a Peace Framework | C31: The 2000 Succession | D31: KMT path | E31: 70 | F31: Preserve the ROC Framework | H31: KMT governing | I31: Cross-Strait Trust (CHI) +10; Strait Tension (CHI) -5; Mainland Economic Dependence +5 | J31: Historical / abstraction | K31: 1 | L31: Written
A32: TAI_su_kmt_consent | B32: No Unification Without Consent | C32: The 2000 Succession | D32: KMT path | E32: 70 | F32: Toward a Peace Framework | H32: KMT governing | I32: Pressure to Negotiate -10; +3% Stability | J32: Historical / abstraction | K32: 3 | L32: Written
A33: TAI_su_kmt_us_ties | B33: Keep Washington Close | C33: The 2000 Succession | D33: KMT path | E33: 70 | F33: A Government of Technocrats | H33: KMT governing | I33: U.S. Confidence in Taipei +8; U.S. Support for Taiwan (CHI) +3 | J33: Historical / abstraction | K33: 3 | L33: Written
... A42: TAI_su_pfp_washington | B42: Reassure Washington | C42: The 2000 Succession | D42: PFP path | E42: 70 | F42: A Pragmatic Strait | H42: PFP governing | I42: U.S. Confidence in Taipei +8 | J42: Historical / abstraction | K42: 1 | L42: Written
A43: TAI_df_root | B43: Consolidate the State, Not the Party | C43: Democratic Fortress | D43: Rule of law | E43: 70 | F43: The Peaceful Transfer of Power | I43: +3% Stability; National Coordination Capacity +5 | J43: Historical / abstraction | K43: 3 | L43: Written
A44: TAI_df_justice_minister | B44: A Reformist Justice Minister | C44: Democratic Fortress | D44: Rule of law | E44: 35 | F44: Consolidate the State, Not the Party | I44: Reform Capacity +5; Corruption -1 level | J44: Historical / abstraction | K44: 1 | L44: Written
A45: TAI_df_unshackle_prosecutors | B45: Unshackle the Prosecutors | C45: Democratic Fortress | D45: Rule of law | E45: 70 | F45: A Reformist Justice Minister | I45: Corruption -1 level; -2% Stability | J45: Historical / abstraction | K45: 1 | L45: Written
A46: TAI_df_professional_judiciary | B46: Professionalize the Judiciary | C46: Democratic Fortress | D46: Rule of law | E46: 70 | F46: Unshackle the Prosecutors | I46: +3% Stability | J46: Historical / abstraction | K46: 1 | L46: Written
A47: TAI_df_grand_justices | B47: Strengthen the Grand Justices | C47: Democratic Fortress | D47: Rule of law | E47: 70 | F47: Professionalize the Judiciary | I47: +3% Stability; +25 Political Power | J47: Historical / abstraction | K47: 1 | L47: Written
A48: TAI_df_special_division | B48: A Special Investigation Division | C48: Democratic Fortress | D48: Rule of law | E48: 70 | F48: Strengthen the Grand Justices | G48: Trust the Ordinary Prosecutors | I48: Corruption -1 level; -3% Stability | J48: Historical / abstraction | K48: 1 | L48: Written
A49: TAI_df_ordinary_prosecutors | B49: Trust the Ordinary Prosecutors | C49: Democratic Fortress | D49: Rule of law | E49: 70 | F49: Strengthen the Grand Justices | G49: A Special Investigation Division | I49: +4% Stability | J49: Historical / abstraction | K49: 3 | L49: Written
A50: TAI_df_black_gold | B50: Clean Up Black Gold | C50: Democratic Fortress | D50: Clean government | E50: 70 | F50: Consolidate the State, Not the Party | I50: Corruption -1 level; -2% Stability | J50: Historical / abstraction | K50: 1 | L50: Written
A51: TAI_df_vote_buying | B51: End the Vote-Buying Economy | C51: Democratic Fortress | D51: Clean government | E51: 70 | F51: Clean Up Black Gold | I51: Corruption -1 level; Party 1 popularity -1% | J51: Historical / abstraction | K51: 1 | L51: Written
A52: TAI_df_sunshine_laws | B52: Sunshine Laws | C52: Democratic Fortress | D52: Clean government | E52: 70 | F52: End the Vote-Buying Economy | H52: Can pass legislation (LY) | I52: Corruption -1 level; +2% Stability | J52: Historical / abstraction | K52: 1 | L52: Written
A53: TAI_df_state_enterprises | B53: Experts, Not Loyalists | C53: Democratic Fortress | D53: Clean government | E53: 70 | F53: Clean Up Black Gold | I53: Timed spirit TAI_professional_state_enterprises (1095 days) | J53: Historical / abstraction | K53: 1 | L53: Written
A54: TAI_df_farmers_associations | B54: Reform the Farmers' Associations | C54: Democratic Fortress | D54: Clean government | E54: 70 | F54: Experts, Not Loyalists | I54: Corruption -1 level; -2% Stability | J54: Historical / abstraction | K54: 1 | L54: Written
A55: TAI_df_special_funds_audit | B55: Audit the Special Funds | C55: Democratic Fortress | D55: Clean government | E55: 70 | F55: Sunshine Laws | I55: Corruption -1 level; +3% Stability | J55: Historical / abstraction | K55: 1 | L55: Written
A56: TAI_df_settle_executive | B56: Settle the Executive Question | C56: Democratic Fortress | D56: Institutions | E56: 70 | F56: Consolidate the State, Not the Party | I56: +3% Stability; +50 Political Power | J56: Historical / abstraction | K56: 1 | L56: Written
A57: TAI_df_legislative_reform | B57: Reform the Legislative Yuan | C57: Democratic Fortress | D57: Institutions | E57: 70 | F57: Settle the Executive Question | H57: Can pass legislation (LY) | I57: Remove spirit TAI_divided_government; +50 Political Power | J57: Historical / abstraction | K57: 1 | L57: Written
A58: TAI_df_end_sntv | B58: End the SNTV System | C58: Democratic Fortress | D58: Institutions | E58: 70 | F58: Reform the Legislative Yuan | H58: Can pass legislation (LY); After 2004.1.1 | I58: Corruption -1 level; +2% Stability | J58: Historical / abstraction | K58: 1 | L58: Written
A59: TAI_df_national_assembly | B59: The National Assembly Votes Itself Out | C59: Democratic Fortress | D59: Institutions | E59: 70 | F59: End the SNTV System | H59: After 2005.1.1 | I59: +5% Stability; +50 Political Power | J59: Historical / abstraction | K59: 1 | L59: Written
A60: TAI_df_control_yuan | B60: Protect the Control Yuan | C60: Democratic Fortress | D60: Institutions | E60: 35 | F60: Settle the Executive Question | I60: Corruption -1 level | J60: Historical / abstraction | K60: 1 | L60: Written
A61: TAI_df_civil_service | B61: A Neutral Civil Service | C61: Democratic Fortress | D61: Institutions | E61: 70 | F61: Protect the Control Yuan | I61: National Coordination Capacity +5; Reform Capacity +5 | J61: Historical / abstraction | K61: 1 | L61: Written
A62: TAI_df_local_government | B62: Empower Local Government | C62: Democratic Fortress | D62: Institutions | E62: 70 | F62: A Neutral Civil Service | I62: National Coordination Capacity +5; +2% Stability | J62: Historical / abstraction | K62: 1 | L62: Written
A63: TAI_df_civil_commissions | B63: Open the Commissions to Civil Society | C63: Democratic Fortress | D63: Civil society | E63: 35 | F63: Consolidate the State, Not the Party | I63: +3% Stability | J63: Historical / abstraction | K63: 1 | L63: Written
A64: TAI_df_party_tv_exit | B64: Get the Parties Out of Television | C64: Democratic Fortress | D64: Civil society | E64: 70 | F64: Open the Commissions to Civil Society | I64: +2% Stability | J64: Historical / abstraction | K64: 1 | L64: Written
A65: TAI_df_public_broadcasting | B65: Expand Public Broadcasting | C65: Democratic Fortress | D65: Civil society | E65: 70 | F65: Get the Parties Out of Television | I65: -1bn Treasury; Pressure to Negotiate -3 | J65: Historical / abstraction | K65: 1 | L65: Written
A66: TAI_df_every_community | B66: Voices of Every Community | C66: Democratic Fortress | D66: Civil society | E66: 70 | F66: Get the Parties Out of Television | I66: Taiwan-Centered Identity +3; +2% Stability | J66: Historical / abstraction | K66: 1 | L66: Written
A67: TAI_df_martial_law_past | B67: Confront the Martial-Law Past | C67: Democratic Fortress | D67: Civil society | E67: 70 | F67: Voices of Every Community | I67: +3% Stability; Military Confidence -5 | J67: Historical / abstraction | K67: 1 | L67: Written
A68: TAI_df_rapid_facts | B68: Rapid Factual Communication | C68: Democratic Fortress | D68: Information resilience | E68: 70 | F68: Expand Public Broadcasting | I68: Pressure to Negotiate -3; +2% Stability | J68: Historical / abstraction | K68: 1 | L68: Written
A69: TAI_df_media_literacy | B69: Media Literacy for All | C69: Democratic Fortress | D69: Information resilience | E69: 70 | F69: Rapid Factual Communication | I69: Pressure to Negotiate -5 | J69: Historical / abstraction | K69: 1 | L69: Written
A70: TAI_df_influence_transparency | B70: Foreign Influence Transparency | C70: Democratic Fortress | D70: Information resilience | E70: 70 | F70: Media Literacy for All | G70: Counter-Disinformation Center | I70: Pressure to Negotiate -5; +2% Stability | J70: Historical / abstraction | K70: 3 | L70: Written
A71: TAI_df_counter_disinfo | B71: Counter-Disinformation Center | C71: Democratic Fortress | D71: Information resilience | E71: 70 | F71: Media Literacy for All | G71: Foreign Influence Transparency | I71: Pressure to Negotiate -8; -2% Stability | J71: Historical / abstraction | K71: 1 | L71: Written
A72: TAI_df_political_dna | B72: Democracy in the Political DNA | C72: Democratic Fortress | D72: Information resilience | E72: 105 | F72: The National Assembly Votes Itself Out; Audit the Special Funds; Foreign Influence Transparency or Counter-Disinformation Center | I72: Remove spirit TAI_young_democracy; Add spirit TAI_consolidated_democracy; Pressure to Negotiate -10 | J72: Historical / abstraction | K72: 5 | L72: Written
A73: TAI_na_rebuild_shield | B73: Rebuild the Shield | C73: The National Army | D73: Civil-military reform | E73: 70 | I73: +15 Army XP; +25 Political Power | J73: Historical / abstraction | K73: 5 | L73: Written
A74: TAI_na_nationalize | B74: Nationalize the Armed Forces | C74: The National Army | D74: Civil-military reform | E74: 70 | F74: Rebuild the Shield; The Peaceful Transfer of Power | I74: Party-Army legacy reduced one step; Military Confidence -5; +2% Stability | J74: Historical / abstraction | K74: 5 | L74: Written
A75: TAI_na_defense_act | B75: Implement the National Defense Act | C75: The National Army | D75: Civil-military reform | E75: 70 | F75: Nationalize the Armed Forces | I75: Party-Army legacy reduced one step; Military Confidence +10; Reform Capacity +5 | J75: Historical / abstraction | K75: 5 | L75: Written
A76: TAI_na_reassure_commanders | B76: Reassure the Commanders | C76: The National Army | D76: Civil-military reform | E76: 35 | F76: Rebuild the Shield | I76: Military Confidence +10; Reform Capacity -5 | J76: Historical / abstraction | K76: 3 | L76: Written
A77: TAI_na_officer_corps | B77: Professional Officer Corps | C77: The National Army | D77: Civil-military reform | E77: 70 | F77: Implement the National Defense Act | I77: Timed spirit TAI_professional_officer_corps (1825 days) | J77: Historical / abstraction | K77: 1 | L77: Written
A78: TAI_na_political_warfare | B78: Reform the Political Warfare Department | C78: The National Army | D78: Civil-military reform | E78: 70 | F78: Professional Officer Corps | I78: +2% Stability; Military Confidence +5 | J78: Historical / abstraction | K78: 1 | L78: Written
A79: TAI_na_joint_command | B79: Joint Command Reform | C79: The National Army | D79: Civil-military reform | E79: 105 | F79: Professional Officer Corps | I79: Defense-in-Depth joint penalty removed; +20 Army XP; +10 Navy XP; +10 Air XP | J79: Historical / abstraction | K79: 1 | L79: Written
A80: TAI_na_reassess_did | B80: Reassess Defense-in-Depth | C80: The National Army | D80: Doctrine | E80: 70 | F80: Rebuild the Shield | I80: +10 Army XP; +25 Political Power | J80: Historical / abstraction | K80: 5 | L80: Written
A81: TAI_na_missile_crisis_lessons | B81: Lessons of the Missile Crisis | C81: The National Army | D81: Doctrine | E81: 35 | F81: Reassess Defense-in-Depth | I81: Research bonus surface_to_air_missiles 50% x1; Reform Capacity +5 | J81: Historical / abstraction | K81: 5 | L81: Written
A82: TAI_na_outside_territory | B82: Decisive Campaign Outside the Territory | C82: The National Army | D82: Doctrine | E82: 70 | F82: Lessons of the Missile Crisis | I82: Posture: Active Defense; Strait Tension (CHI) +4; Military Confidence -5 | J82: Historical / abstraction | K82: 3 | L82: Written
A83: TAI_na_effective_deterrence | B83: Effective Deterrence, Resolute Defense | C83: The National Army | D83: Doctrine | E83: 70 | F83: Decisive Campaign Outside the Territory | I83: +15 Navy XP; +15 Air XP | J83: Historical / abstraction | K83: 1 | L83: Written
A84: TAI_na_air_sea_interdiction | B84: Air-Sea Interdiction | C84: The National Army | D84: Doctrine | E84: 105 | F84: Effective Deterrence, Resolute Defense | I84: Research bonus naval_anti_ship_missiles 50% x2; +15 Navy XP | J84: Historical / abstraction | K84: 1 | L84: Written
A85: TAI_na_hf2e | B85: The HF-2E Program | C85: The National Army | D85: Doctrine | E85: 105 | F85: Effective Deterrence, Resolute Defense | H85: Can pass legislation (LY) | I85: Research bonus cruise_missiles 75% x2; Strait Tension (CHI) +8; U.S. Confidence in Taipei -5 | J85: Historical / abstraction | K85: 1 | L85: Written
A86: TAI_na_hf2e_extended | B86: Extended-Range Countermeasures | C86: The National Army | D86: Doctrine | E86: 140 | F86: The HF-2E Program | I86: Research bonus ground_launched_cruise_missiles 75% x2; Strait Tension (CHI) +8 | J86: Historical / abstraction | K86: 0 | L86: Written
A87: TAI_na_info_warfare | B87: Information and Electronic Warfare Command | C87: The National Army | D87: Doctrine | E87: 70 | F87: Effective Deterrence, Resolute Defense | I87: Research bonus encryption 50% x2; Reform Capacity +5 | J87: Historical / abstraction | K87: 1 | L87: Written
A88: TAI_na_layered_air_defense | B88: Layered Air and Missile Defense | C88: The National Army | D88: Doctrine | E88: 105 | F88: Lessons of the Missile Crisis | I88: Research bonus surface_to_air_missiles 75% x2; Build: anti air; Build: radar station | J88: Historical / abstraction | K88: 1 | L88: Written
A89: TAI_na_harden_island | B89: Harden the Island | C89: The National Army | D89: Doctrine | E89: 70 | F89: Lessons of the Missile Crisis | I89: Build: air base; Timed spirit TAI_hardened_shelters (1825 days); +10 Army XP | J89: Historical / abstraction | K89: 1 | L89: Written
A90: TAI_na_repair_runways | B90: Repair the Runways | C90: The National Army | D90: Doctrine | E90: 70 | F90: Harden the Island | I90: +15 Air XP; Timed spirit TAI_runway_repair_teams (1825 days) | J90: Historical / abstraction | K90: 1 | L90: Written
A91: TAI_na_mine_approaches | B91: Mine the Approaches | C91: The National Army | D91: Doctrine | E91: 70 | F91: Harden the Island | I91: +15 Navy XP; Timed spirit TAI_mined_approaches (1825 days) | J91: Historical / abstraction | K91: 1 | L91: Written
A92: TAI_na_rapid_redeploy | B92: Rapid Internal Redeployment | C92: The National Army | D92: Doctrine | E92: 70 | F92: Repair the Runways | I92: Build: infrastructure; +10 Army XP | J92: Historical / abstraction | K92: 1 | L92: Written
A93: TAI_na_hard_roc | B93: Hard ROC | C93: The National Army | D93: Doctrine | E93: 105 | F93: Mine the Approaches | H93: After 2008.1.1 or KMT governing | I93: Posture: Hard ROC; Strait Tension (CHI) -3 | J93: Historical / abstraction | K93: 1 | L93: Written
A94: TAI_na_mobile_fires | B94: Mobile Coastal Fires | C94: The National Army | D94: Doctrine | E94: 105 | F94: Mine the Approaches or Air-Sea Interdiction | I94: Research bonus naval_anti_ship_missiles 50% x2; +10 Army XP | J94: Historical / abstraction | K94: 1 | L94: Written
A95: TAI_na_disperse | B95: Disperse and Survive | C95: The National Army | D95: Doctrine | E95: 70 | F95: Mobile Coastal Fires | I95: Timed spirit TAI_dispersed_forces (1825 days) | J95: Historical / abstraction | K95: 1 | L95: Written
A96: TAI_na_unmanned | B96: Unmanned Systems | C96: The National Army | D96: Doctrine | E96: 105 | F96: Disperse and Survive | H96: After 2012.1.1 | I96: Research bonus air_drones 75% x2; Research bonus land_drones 50% x1 | J96: Historical / abstraction | K96: 1 | L96: Written
A97: TAI_na_odc | B97: Overall Defense Concept | C97: The National Army | D97: Doctrine | E97: 105 | F97: Unmanned Systems | H97: After 2017.1.1 | I97: Posture: Asymmetric; U.S. Confidence in Taipei +5 | J97: Historical / abstraction | K97: 1 | L97: Written
A98: TAI_na_hybrid | B98: Hybrid Resilience | C98: The National Army | D98: Doctrine | E98: 105 | F98: Air-Sea Interdiction or Hard ROC or Overall Defense Concept; Joint Command Reform | I98: Posture: Hybrid; +15 Army XP | J98: Historical / abstraction | K98: 1 | L98: Written
A99: TAI_na_whole_of_society | B99: Whole-of-Society Defense | C99: The National Army | D99: Doctrine | E99: 105 | F99: Hybrid Resilience; Territorial Defense Brigades | I99: Add spirit TAI_whole_of_society_defense; +5% War Support | J99: Historical / abstraction | K99: 1 | L99: Written
A100: TAI_na_fortress_taiwan | B100: Fortress Taiwan | C100: The National Army | D100: Doctrine | E100: 140 | F100: Whole-of-Society Defense | I100: Add spirit TAI_fortress_taiwan; Strait Tension (CHI) +5 | J100: Historical / abstraction | K100: 1 | L100: Written
A101: TAI_na_manpower_question | B101: The Manpower Question | C101: The National Army | D101: Manpower | E101: 35 | F101: Rebuild the Shield | I101: +25 Political Power | J101: Historical / abstraction | K101: 5 | L101: Written
A102: TAI_na_volunteer_reserve_split | B102: Volunteer / Reserve Split | C102: The National Army | D102: Manpower | E102: 70 | F102: The Manpower Question | G102: Retain Extended Conscription; Professional First-Line Force | I102: Add spirit TAI_volunteer_reserve_split | J102: Historical / abstraction | K102: 5 | L102: Written
A103: TAI_na_professional_force | B103: Professional First-Line Force | C103: The National Army | D103: Manpower | E103: 70 | F103: The Manpower Question | G103: Retain Extended Conscription; Volunteer / Reserve Split | I103: Add spirit TAI_professional_force | J103: Historical / abstraction | K103: 1 | L103: Written
A104: TAI_na_extended_conscription | B104: Retain Extended Conscription | C104: The National Army | D104: Manpower | E104: 70 | F104: The Manpower Question | G104: Professional First-Line Force; Volunteer / Reserve Split | I104: Add spirit TAI_extended_conscription | J104: Historical / abstraction | K104: 1 | L104: Written
A105: TAI_na_reserve_audit | B105: Reserve Readiness Audit | C105: The National Army | D105: Manpower | E105: 35 | F105: Volunteer / Reserve Split or Professional First-Line Force or Retain Extended Conscription | I105: +10 Army XP; Reform Capacity +5 | J105: Historical / abstraction | K105: 1 | L105: Written
A106: TAI_na_reserve_reform | B106: Reserve Reform | C106: The National Army | D106: Manpower | E106: 105 | F106: Reserve Readiness Audit | I106: Remove spirit TAI_uneven_reserves; -2bn Treasury | J106: Historical / abstraction | K106: 1 | L106: Written
A107: TAI_na_nco_initiative | B107: NCO and Junior Leader Initiative | C107: The National Army | D107: Manpower | E107: 70 | F107: Volunteer / Reserve Split or Professional First-Line Force or Retain Extended Conscription | I107: Timed spirit TAI_junior_leader_initiative (1825 days) | J107: Historical / abstraction | K107: 1 | L107: Written
A108: TAI_na_territorial_defense | B108: Territorial Defense Brigades | C108: The National Army | D108: Manpower | E108: 105 | F108: Reserve Reform | I108: +20 Army XP; +3% War Support | J108: Historical / abstraction | K108: 1 | L108: Written
...

Sheet Spirits
A1: Spirit ID | B1: Name | C1: Starting spirit | D1: Modifiers | E1: Granted by | F1: Description
A2: TAI_young_democracy | B2: Young Democracy | C2: Yes | D2: political_power_factor = -0.05; democratic_drift = 0.02 | E2: Game start | F2: Direct presidential elections are only four years old, and many institutions still carry habits from one-party rule. Public enthusiasm for democracy is high, but reform is slow and contested.
A3: TAI_party_army | B3: Legacy of the Party-Army | C3: Yes | D3: political_power_factor = -0.05; experience_gain_army = -0.10 | E3: Game start | F3: For decades the armed forces swore loyalty to the Kuomintang as well as the state. Many senior officers are uneasy about serving a government formed by another party.
A4: TAI_party_army_reduced | B4: Legacy of the Party-Army | C4: No | D4: experience_gain_army = -0.05 | E4: Nationalize the Armed Forces | F4: The armed forces now serve the constitution in law, but old habits fade slowly.
A5: TAI_did_legacy | B5: Defense-in-Depth Legacy | C5: Yes | D5: army_defence_factor = 0.05; max_dig_in = 2; naval_damage_factor = -0.05; air_attack_factor = -0.05; planning_speed = -0.05 | E5: Game start | F5: Our forces were built to defeat a landing on the beaches. They dig in well but are poorly prepared to strike at sea or fight as a joint force.
A6: TAI_did_legacy_reformed | B6: Defense-in-Depth Legacy | C6: No | D6: army_defence_factor = 0.05; max_dig_in = 2 | E6: Joint Command Reform | F6: Joint command has removed the worst seams between the services, but our doctrine still centers on the beaches.
A7: TAI_uneven_reserves | B7: Large but Uneven Reserve System | C7: Yes | D7: training_time_factor = 0.10; army_org_factor = -0.03 | E7: Game start | F7: Millions of men are listed as reservists after conscription, but refresher training is short and irregular.
A8: TAI_limited_absorption | B8: Advanced Procurement, Limited Absorption | C8: Yes | D8: experience_gain_air = -0.05; experience_gain_navy = -0.05 | E8: Game start | F8: The F-16s, Mirage 2000-5s and new frigates of the 1990s arrived faster than crews, mechanics and spare parts could keep up.
A9: TAI_divided_government | B9: Divided Government | C9: No | D9: political_power_factor = -0.10; stability_factor = -0.03 | E9: A Government Without a Majority; Reunite the Pan-Blue Camp; Reform the Legislative Yuan | F9: The president's party does not control the Legislative Yuan. Every budget and reform must be negotiated with the opposition.
A10: TAI_consolidated_democracy | B10: Consolidated Democracy | C10: No | D10: stability_factor = 0.05; political_power_factor = 0.05; foreign_influence_defense_modifier = 0.15; drift_defence_factor = 0.15 | E10: Democracy in the Political DNA | F10: Peaceful alternation in power, independent courts and a free press are now accepted by every major party.
A11: TAI_recession_relief | B11: Recession Relief | C11: No | D11: stability_factor = 0.03 | E11: Weather the 2001 Recession | F11: Job programmes and targeted relief keep the technology downturn from becoming a social crisis.
A12: TAI_technocratic_cabinet | B12: A Cabinet of Technocrats | C12: No | D12: research_speed_factor = 0.03; production_factory_efficiency_gain_factor = 0.03; political_power_factor = -0.03 | E12: A Government of Technocrats | F12: Experienced administrators run the ministries, trading political charisma for steady delivery.
... A49: TAI_impossible_to_coerce | B49: Impossible to Coerce | C49: No | D49: stability_factor = 0.05; war_support_factor = 0.05; foreign_influence_defense_modifier = 0.20; army_core_defence_factor = 0.05 | E49: Impossible to Coerce at an Acceptable Price | F49: Taiwan does not have to be impossible to hurt. It has to be impossible to coerce at an acceptable price.

Sheet Variables
A1: Variable | B1: Meaning | C1: Scope | D1: Start value | E1: Status | F1: Source
A2: TAI_us_confidence | B2: U.S. Confidence in Taipei | C2: TAI | D2: 60 | E2: New; moved by focuses | F2: Pass VI (separate from commitment)
A3: TAI_military_confidence | B3: Military Confidence | C3: TAI | D3: 55 | E3: New; moved by focuses | F3: Pass IV
A4: TAI_reform_capacity | B4: Reform Capacity | C4: TAI | D4: 50 | E4: New; moved by focuses | F4: Pass IV
A5: TAI_mainland_dependence | B5: Mainland Economic Dependence | C5: TAI | D5: 30 | E5: New; moved by focuses | F5: Pass VI (separate from trust)
A6: TAI_semiconductor_security | B6: Semiconductor Supply Security | C6: TAI | D6: 85 | E6: New; moved by focuses | F6: Directive section 4
A7: TAI_pressure_to_negotiate | B7: Pressure to Negotiate | C7: TAI | D7: 5 | E7: New; moved by focuses | F7: Pass VI
A8: TAI_taiwanese_identity | B8: Taiwan-Centered Identity | C8: TAI | D8: 40 | E8: New; moved by focuses | F8: Pass III / thesis
A9: TAI_national_coordination | B9: National Coordination Capacity | C9: TAI | D9: 40 | E9: New; moved by focuses | F9: Pass VI (30-page draft)
A10: TAI_defense_posture | B10: Defense posture (1 DiD, 2 Active, 3 Hard ROC, 4 Asymmetric, 5 Hybrid) | C10: TAI | D10: 1 | E10: New; set by doctrine focuses | F10: Pass IV
A11: CHI_taiwan_strait_tension | B11: Cross-Strait Tension | C11: CHI | D11: 20 | E11: Existing MD variable, reused | F11: Millennium Dawn
A12: CHI_TAI_trust | B12: Cross-Strait political trust | C12: CHI | D12: 50 | E12: Existing MD variable, reused | F12: Millennium Dawn
A13: CHI_taiwan_us_support | B13: U.S. Security Commitment | C13: CHI | D13: 85 | E13: Existing MD variable, reused | F13: Millennium Dawn
A15: Start values are proposed balance values on 0-100 scales, not historical measurements. CHI values are Millennium Dawn's existing history settings.

Sheet Files Changed
A1: File | B1: Change | C1: Lines added | D1: Lines deleted
A2: common/national_focus/05_taiwan.txt | B2: New file: taiwan_focus tree, 247 focuses | C2: 5516 | D2: 0
A3: common/ideas/05_taiwan.txt | B3: Added 54 Blue Tiger national spirits | C3: 467 | D3: 0
A4: common/scripted_triggers/99_TAI_scripted_triggers.txt | B4: Added 7 triggers (government camp, LY majority, roots ready) | C4: 65 | D4: 0
A5: common/scripted_effects/99_TAI_scripted_effects.txt | B5: Added 3 effects | C5: 31 | D5: 0
A6: history/countries/TAI - Taiwan.txt | B6: Added 5 starting spirits and 9 state variables | C6: 15 | D6: 0
A7: localisation/english/MD_focus_TAI_l_english.yml | B7: Added all focus, spirit, variable and tooltip text | C7: 611 | D7: 0
A8: Changelog.txt | B8: Added one line under v2.0.1 Content | C8: 1 | D8: 0
A9: Total | C9: =SUM(C2:C8) -> 6706 | D9: =SUM(D2:D8) -> 0
A11: Line counts from git diff --stat on branch obt-taiwan-overhaul, 16 Oct 2026. All changes are uncommitted.
